MANIFEST.in
README.rst
setup.py
docs/HISTORY.txt
ftw/__init__.py
ftw.publisher.example.egg-info/PKG-INFO
ftw.publisher.example.egg-info/SOURCES.txt
ftw.publisher.example.egg-info/dependency_links.txt
ftw.publisher.example.egg-info/entry_points.txt
ftw.publisher.example.egg-info/namespace_packages.txt
ftw.publisher.example.egg-info/not-zip-safe
ftw.publisher.example.egg-info/requires.txt
ftw.publisher.example.egg-info/top_level.txt
ftw/publisher/__init__.py
ftw/publisher/example/__init__.py
ftw/publisher/example/config.py
ftw/publisher/example/configure.zcml
ftw/publisher/example/eventhandlers.py
ftw/publisher/example/interfaces.py
ftw/publisher/example/receiver.zcml
ftw/publisher/example/sender.zcml
ftw/publisher/example/utils.py
ftw/publisher/example/version.txt
ftw/publisher/example/browser/__init__.py
ftw/publisher/example/browser/controller.py
ftw/publisher/example/profiles/receiver/metadata.xml
ftw/publisher/example/profiles/sender/metadata.xml
ftw/publisher/example/profiles/workflow/metadata.xml
ftw/publisher/example/profiles/workflow/workflows.xml
ftw/publisher/example/profiles/workflow/workflows/publisher_workflow/definition.xml
ftw/publisher/example/profiles/workflow/workflows/publisher_workflow/scripts/before_publish.py
ftw/publisher/example/profiles/workflow/workflows/publisher_workflow/scripts/before_reject.py
ftw/publisher/example/profiles/workflow/workflows/publisher_workflow/scripts/before_retract.py
ftw/publisher/example/profiles/workflow/workflows/publisher_workflow/scripts/before_revise.py
ftw/publisher/example/profiles/workflow/workflows/publisher_workflow/scripts/before_submit.py