Metadata-Version: 1.0
Name: ftw.publisher.example
Version: 1.0
Summary: Example workflow integration for ftw.publisher's staging and publishing system
Home-page: https://github.com/4teamwork/ftw.publisher.example
Author: Jonas Baumann
Author-email: mailto:info@4teamwork.ch
License: GPL2
Keywords: ftw publisher example
Platform: UNKNOWN
Classifier: Framework :: Plone
Classifier: Framework :: Zope2
Classifier: Programming Language :: Python
